{
  "data": {
    "401778306": {
      "temperatureF": 63,
      "windSpeedMph": 7.0,
      "shortForecast": "Chance Rain Showers",
      "detailedForecast": ""
    },
    "401778307": {
      "temperatureF": 70,
      "windSpeedMph": 7.0,
      "shortForecast": "Slight Chance Rain Showers",
      "detailedForecast": ""
    },
    "401779840": {
      "temperatureF": 38,
      "windSpeedMph": 5.0,
      "shortForecast": "Mostly Clear",
      "detailedForecast": ""
    },
    "401779841": {
      "temperatureF": 54,
      "windSpeedMph": 10.0,
      "shortForecast": "Clear",
      "detailedForecast": ""
    },
    "401779842": {
      "temperatureF": 44,
      "windSpeedMph": 10.0,
      "shortForecast": "Clear",
      "detailedForecast": ""
    },
    "401772612": {
      "temperatureF": 51,
      "windSpeedMph": 13.0,
      "shortForecast": "Rain Showers",
      "detailedForecast": ""
    },
    "401779843": {
      "temperatureF": 56,
      "windSpeedMph": 17.0,
      "shortForecast": "Rain",
      "detailedForecast": ""
    },
    "401772613": {
      "temperatureF": 22,
      "windSpeedMph": 25.0,
      "shortForecast": "Snow Showers",
      "detailedForecast": ""
    },
    "401772802": {
      "temperatureF": 50,
      "windSpeedMph": 25.0,
      "shortForecast": "Rain",
      "detailedForecast": ""
    },
    "401772803": {
      "temperatureF": 45,
      "windSpeedMph": 10.0,
      "shortForecast": "Mostly Clear",
      "detailedForecast": ""
    },
    "401772934": {
      "temperatureF": 75,
      "windSpeedMph": 6.0,
      "shortForecast": "Mostly Cloudy",
      "detailedForecast": ""
    },
    "401772911": {
      "temperatureF": 47,
      "windSpeedMph": 5.0,
      "shortForecast": "Chance Rain Showers",
      "detailedForecast": ""
    },
    "401772912": {
      "temperatureF": 58,
      "windSpeedMph": 13.0,
      "shortForecast": "Light Rain Likely",
      "detailedForecast": ""
    },
    "401772913": {
      "temperatureF": 35,
      "windSpeedMph": 8.0,
      "shortForecast": "Partly Cloudy",
      "detailedForecast": ""
    },
    "401772804": {
      "temperatureF": 47,
      "windSpeedMph": 7.0,
      "shortForecast": "Rain Showers",
      "detailedForecast": ""
    },
    "401778308": {
      "temperatureF": 45,
      "windSpeedMph": 8.0,
      "shortForecast": "Chance Light Rain",
      "detailedForecast": ""
    },
    "401778309": {
      "temperatureF": 75,
      "windSpeedMph": 10.0,
      "shortForecast": "Mostly Cloudy",
      "detailedForecast": ""
    },
    "401778312": {
      "temperatureF": 78,
      "windSpeedMph": 6.0,
      "shortForecast": "Scattered Rain Showers",
      "detailedForecast": ""
    },
    "401772710": {
      "temperatureF": 51,
      "windSpeedMph": 13.0,
      "shortForecast": "Rain Showers",
      "detailedForecast": ""
    },
    "401772622": {
      "temperatureF": 27,
      "windSpeedMph": 16.0,
      "shortForecast": "Clear",
      "detailedForecast": ""
    },
    "401778315": {
      "temperatureF": 48,
      "windSpeedMph": 5.0,
      "shortForecast": "Clear",
      "detailedForecast": ""
    },
    "401778316": {
      "temperatureF": 48,
      "windSpeedMph": 15.0,
      "shortForecast": "Rain Showers",
      "detailedForecast": ""
    },
    "401778317": {
      "temperatureF": 48,
      "windSpeedMph": 8.0,
      "shortForecast": "Chance Rain Showers",
      "detailedForecast": ""
    },
    "401778318": {
      "temperatureF": 43,
      "windSpeedMph": 8.0,
      "shortForecast": "Sunny",
      "detailedForecast": ""
    },
    "401778319": {
      "temperatureF": 68,
      "windSpeedMph": 5.0,
      "shortForecast": "Mostly Cloudy",
      "detailedForecast": ""
    },
    "401778320": {
      "temperatureF": 53,
      "windSpeedMph": 3.0,
      "shortForecast": "Clear",
      "detailedForecast": ""
    },
    "401778321": {
      "temperatureF": 42,
      "windSpeedMph": 0.0,
      "shortForecast": "Mostly Clear",
      "detailedForecast": ""
    },
    "401778322": {
      "temperatureF": 67,
      "windSpeedMph": 12.0,
      "shortForecast": "Slight Chance Rain Showers",
      "detailedForecast": ""
    },
    "401772953": {
      "temperatureF": 24,
      "windSpeedMph": 17.0,
      "shortForecast": "Light Snow",
      "detailedForecast": ""
    },
    "401772954": {
      "temperatureF": 44,
      "windSpeedMph": 7.0,
      "shortForecast": "Scattered Rain Showers",
      "detailedForecast": ""
    },
    "401772807": {
      "temperatureF": 50,
      "windSpeedMph": 25.0,
      "shortForecast": "Rain",
      "detailedForecast": ""
    },
    "401772809": {
      "temperatureF": 45,
      "windSpeedMph": 10.0,
      "shortForecast": "Mostly Clear",
      "detailedForecast": ""
    },
    "401772916": {
      "temperatureF": 75,
      "windSpeedMph": 6.0,
      "shortForecast": "Mostly Cloudy",
      "detailedForecast": ""
    },
    "401772808": {
      "temperatureF": 47,
      "windSpeedMph": 5.0,
      "shortForecast": "Chance Rain Showers",
      "detailedForecast": ""
    },
    "401772952": {
      "temperatureF": 58,
      "windSpeedMph": 13.0,
      "shortForecast": "Light Rain Likely",
      "detailedForecast": ""
    },
    "401772917": {
      "temperatureF": 48,
      "windSpeedMph": 20.0,
      "shortForecast": "Mostly Cloudy",
      "detailedForecast": ""
    },
    "401772935": {
      "temperatureF": 50,
      "windSpeedMph": 2.0,
      "shortForecast": "Patchy Fog",
      "detailedForecast": ""
    }
  }
}