{
  "data": {
    "401772823": {
      "temperatureF": 8,
      "windSpeedMph": 6.0,
      "shortForecast": "Mostly Cloudy",
      "detailedForecast": ""
    },
    "401778303": {
      "temperatureF": 27,
      "windSpeedMph": 10.0,
      "shortForecast": "Mostly Clear",
      "detailedForecast": ""
    },
    "401778304": {
      "temperatureF": 54,
      "windSpeedMph": 15.0,
      "shortForecast": "Mostly Cloudy",
      "detailedForecast": ""
    },
    "401778305": {
      "temperatureF": 28,
      "windSpeedMph": 10.0,
      "shortForecast": "Clear",
      "detailedForecast": ""
    },
    "401772949": {
      "temperatureF": 53,
      "windSpeedMph": 13.0,
      "shortForecast": "Rain",
      "detailedForecast": ""
    },
    "401778306": {
      "temperatureF": 20,
      "windSpeedMph": 7.0,
      "shortForecast": "Clear",
      "detailedForecast": ""
    },
    "401778307": {
      "temperatureF": 60,
      "windSpeedMph": 12.0,
      "shortForecast": "Mostly Clear",
      "detailedForecast": ""
    },
    "401779840": {
      "temperatureF": 21,
      "windSpeedMph": 9.0,
      "shortForecast": "Mostly Clear",
      "detailedForecast": ""
    },
    "401779841": {
      "temperatureF": 32,
      "windSpeedMph": 5.0,
      "shortForecast": "Widespread Frost",
      "detailedForecast": ""
    },
    "401779842": {
      "temperatureF": 17,
      "windSpeedMph": 0.0,
      "shortForecast": "Clear",
      "detailedForecast": ""
    },
    "401772612": {
      "temperatureF": 17,
      "windSpeedMph": 10.0,
      "shortForecast": "Mostly Clear",
      "detailedForecast": ""
    },
    "401779843": {
      "temperatureF": 51,
      "windSpeedMph": 6.0,
      "shortForecast": "Chance Light Rain",
      "detailedForecast": ""
    },
    "401772613": {
      "temperatureF": 7,
      "windSpeedMph": 15.0,
      "shortForecast": "Mostly Cloudy",
      "detailedForecast": ""
    },
    "401772802": {
      "temperatureF": 17,
      "windSpeedMph": 10.0,
      "shortForecast": "Slight Chance Snow Showers",
      "detailedForecast": ""
    },
    "401772803": {
      "temperatureF": 15,
      "windSpeedMph": 5.0,
      "shortForecast": "Clear",
      "detailedForecast": ""
    },
    "401772934": {
      "temperatureF": 68,
      "windSpeedMph": 13.0,
      "shortForecast": "Chance Showers And Thunderstorms",
      "detailedForecast": ""
    },
    "401772911": {
      "temperatureF": 17,
      "windSpeedMph": 12.0,
      "shortForecast": "Mostly Clear",
      "detailedForecast": ""
    },
    "401772912": {
      "temperatureF": 16,
      "windSpeedMph": 3.0,
      "shortForecast": "Clear",
      "detailedForecast": ""
    },
    "401772913": {
      "temperatureF": 39,
      "windSpeedMph": 7.0,
      "shortForecast": "Mostly Clear",
      "detailedForecast": ""
    },
    "401772804": {
      "temperatureF": 19,
      "windSpeedMph": 12.0,
      "shortForecast": "Mostly Clear",
      "detailedForecast": ""
    },
    "401778308": {
      "temperatureF": 34,
      "windSpeedMph": 1.0,
      "shortForecast": "Partly Cloudy",
      "detailedForecast": ""
    },
    "401778309": {
      "temperatureF": 69,
      "windSpeedMph": 21.0,
      "shortForecast": "Chance Showers And Thunderstorms",
      "detailedForecast": ""
    },
    "401772710": {
      "temperatureF": 17,
      "windSpeedMph": 10.0,
      "shortForecast": "Mostly Clear",
      "detailedForecast": ""
    },
    "401772622": {
      "temperatureF": 22,
      "windSpeedMph": 10.0,
      "shortForecast": "Clear",
      "detailedForecast": ""
    },
    "401772953": {
      "temperatureF": 8,
      "windSpeedMph": 10.0,
      "shortForecast": "Slight Chance Light Snow",
      "detailedForecast": ""
    }
  }
}