{
  "data": {
    "401752788": {
      "temperatureF": 32,
      "windSpeedMph": 0.0,
      "shortForecast": "Clear",
      "detailedForecast": ""
    },
    "401752916": {
      "temperatureF": 22,
      "windSpeedMph": 2.0,
      "shortForecast": "Mostly Cloudy",
      "detailedForecast": ""
    },
    "401762870": {
      "temperatureF": 31,
      "windSpeedMph": 20.0,
      "shortForecast": "Snow Showers Likely",
      "detailedForecast": ""
    },
    "401762871": {
      "temperatureF": 21,
      "windSpeedMph": 10.0,
      "shortForecast": "Mostly Clear",
      "detailedForecast": ""
    },
    "401772621": {
      "temperatureF": 33,
      "windSpeedMph": 10.0,
      "shortForecast": "Mostly Clear",
      "detailedForecast": ""
    },
    "401760421": {
      "temperatureF": 30,
      "windSpeedMph": 3.0,
      "shortForecast": "Mostly Cloudy",
      "detailedForecast": ""
    },
    "401762442": {
      "temperatureF": 46,
      "windSpeedMph": 0.0,
      "shortForecast": "Partly Cloudy",
      "detailedForecast": ""
    },
    "401760422": {
      "temperatureF": 36,
      "windSpeedMph": 2.0,
      "shortForecast": "Mostly Cloudy",
      "detailedForecast": ""
    },
    "401752924": {
      "temperatureF": 23,
      "windSpeedMph": 10.0,
      "shortForecast": "Clear",
      "detailedForecast": ""
    },
    "401752792": {
      "temperatureF": 51,
      "windSpeedMph": 0.0,
      "shortForecast": "Mostly Cloudy",
      "detailedForecast": ""
    },
    "401756961": {
      "temperatureF": 55,
      "windSpeedMph": 0.0,
      "shortForecast": "Mostly Clear",
      "detailedForecast": ""
    },
    "401752921": {
      "temperatureF": 26,
      "windSpeedMph": 15.0,
      "shortForecast": "Partly Cloudy",
      "detailedForecast": ""
    },
    "401756968": {
      "temperatureF": 26,
      "windSpeedMph": 13.0,
      "shortForecast": "Slight Chance Snow Showers",
      "detailedForecast": ""
    },
    "401754611": {
      "temperatureF": 27,
      "windSpeedMph": 15.0,
      "shortForecast": "Chance Snow Showers",
      "detailedForecast": ""
    },
    "401752787": {
      "temperatureF": 25,
      "windSpeedMph": 6.0,
      "shortForecast": "Mostly Clear",
      "detailedForecast": ""
    },
    "401752790": {
      "temperatureF": 38,
      "windSpeedMph": 3.0,
      "shortForecast": "Clear",
      "detailedForecast": ""
    },
    "401756962": {
      "temperatureF": 46,
      "windSpeedMph": 0.0,
      "shortForecast": "Partly Cloudy",
      "detailedForecast": ""
    },
    "401756965": {
      "temperatureF": 30,
      "windSpeedMph": 0.0,
      "shortForecast": "Mostly Cloudy",
      "detailedForecast": ""
    },
    "401756966": {
      "temperatureF": 34,
      "windSpeedMph": 0.0,
      "shortForecast": "Mostly Clear",
      "detailedForecast": ""
    },
    "401762519": {
      "temperatureF": 60,
      "windSpeedMph": 18.0,
      "shortForecast": "Mostly Cloudy",
      "detailedForecast": ""
    },
    "401762872": {
      "temperatureF": 24,
      "windSpeedMph": 15.0,
      "shortForecast": "Slight Chance Snow Showers",
      "detailedForecast": ""
    },
    "401762875": {
      "temperatureF": 25,
      "windSpeedMph": 9.0,
      "shortForecast": "Partly Cloudy",
      "detailedForecast": ""
    },
    "401756963": {
      "temperatureF": 40,
      "windSpeedMph": 3.0,
      "shortForecast": "Partly Cloudy",
      "detailedForecast": ""
    },
    "401757310": {
      "temperatureF": 30,
      "windSpeedMph": 10.0,
      "shortForecast": "Clear",
      "detailedForecast": ""
    },
    "401757311": {
      "temperatureF": 51,
      "windSpeedMph": 5.0,
      "shortForecast": "Partly Cloudy",
      "detailedForecast": ""
    },
    "401761663": {
      "temperatureF": 27,
      "windSpeedMph": 7.0,
      "shortForecast": "Mostly Cloudy",
      "detailedForecast": ""
    },
    "401757312": {
      "temperatureF": 27,
      "windSpeedMph": 5.0,
      "shortForecast": "Clear",
      "detailedForecast": ""
    },
    "401761664": {
      "temperatureF": 36,
      "windSpeedMph": 10.0,
      "shortForecast": "Clear",
      "detailedForecast": ""
    },
    "401761661": {
      "temperatureF": 20,
      "windSpeedMph": 23.0,
      "shortForecast": "Partly Cloudy",
      "detailedForecast": ""
    },
    "401761665": {
      "temperatureF": 40,
      "windSpeedMph": 5.0,
      "shortForecast": "Partly Cloudy",
      "detailedForecast": ""
    },
    "401761667": {
      "temperatureF": 51,
      "windSpeedMph": 5.0,
      "shortForecast": "Mostly Cloudy",
      "detailedForecast": ""
    },
    "401762517": {
      "temperatureF": 38,
      "windSpeedMph": 0.0,
      "shortForecast": "Partly Cloudy",
      "detailedForecast": ""
    },
    "401752917": {
      "temperatureF": 48,
      "windSpeedMph": 7.0,
      "shortForecast": "Cloudy",
      "detailedForecast": ""
    },
    "401772785": {
      "temperatureF": 31,
      "windSpeedMph": 23.0,
      "shortForecast": "Snow Likely And Patchy Blowing Snow",
      "detailedForecast": ""
    },
    "401772786": {
      "temperatureF": 31,
      "windSpeedMph": 5.0,
      "shortForecast": "Clear",
      "detailedForecast": ""
    },
    "401772892": {
      "temperatureF": 61,
      "windSpeedMph": 14.0,
      "shortForecast": "Mostly Cloudy",
      "detailedForecast": ""
    },
    "401772893": {
      "temperatureF": 33,
      "windSpeedMph": 12.0,
      "shortForecast": "Mostly Clear",
      "detailedForecast": ""
    },
    "401772895": {
      "temperatureF": 50,
      "windSpeedMph": 12.0,
      "shortForecast": "Mostly Clear",
      "detailedForecast": ""
    },
    "401772894": {
      "temperatureF": 34,
      "windSpeedMph": 6.0,
      "shortForecast": "Clear",
      "detailedForecast": ""
    },
    "401772896": {
      "temperatureF": 48,
      "windSpeedMph": 7.0,
      "shortForecast": "Cloudy",
      "detailedForecast": ""
    },
    "401772789": {
      "temperatureF": 27,
      "windSpeedMph": 15.0,
      "shortForecast": "Chance Snow Showers",
      "detailedForecast": ""
    },
    "401772931": {
      "temperatureF": 31,
      "windSpeedMph": 13.0,
      "shortForecast": "Mostly Clear",
      "detailedForecast": ""
    },
    "401772821": {
      "temperatureF": 30,
      "windSpeedMph": 6.0,
      "shortForecast": "Clear",
      "detailedForecast": ""
    },
    "401777352": {
      "temperatureF": 24,
      "windSpeedMph": 13.0,
      "shortForecast": "Partly Cloudy",
      "detailedForecast": ""
    },
    "401826791": {
      "temperatureF": 35,
      "windSpeedMph": 0.0,
      "shortForecast": "Mostly Clear",
      "detailedForecast": ""
    },
    "401777328": {
      "temperatureF": 34,
      "windSpeedMph": 6.0,
      "shortForecast": "Clear",
      "detailedForecast": ""
    },
    "401772902": {
      "temperatureF": 30,
      "windSpeedMph": 18.0,
      "shortForecast": "Snow Showers Likely And Patchy Blowing Snow",
      "detailedForecast": ""
    },
    "401772898": {
      "temperatureF": 31,
      "windSpeedMph": 23.0,
      "shortForecast": "Snow Likely And Patchy Blowing Snow",
      "detailedForecast": ""
    },
    "401772790": {
      "temperatureF": 33,
      "windSpeedMph": 12.0,
      "shortForecast": "Mostly Clear",
      "detailedForecast": ""
    },
    "401772792": {
      "temperatureF": 50,
      "windSpeedMph": 12.0,
      "shortForecast": "Mostly Clear",
      "detailedForecast": ""
    },
    "401772793": {
      "temperatureF": 50,
      "windSpeedMph": 10.0,
      "shortForecast": "Clear",
      "detailedForecast": ""
    },
    "401772791": {
      "temperatureF": 33,
      "windSpeedMph": 13.0,
      "shortForecast": "Mostly Clear",
      "detailedForecast": ""
    },
    "401772897": {
      "temperatureF": 22,
      "windSpeedMph": 9.0,
      "shortForecast": "Partly Cloudy",
      "detailedForecast": ""
    },
    "401772932": {
      "temperatureF": 27,
      "windSpeedMph": 3.0,
      "shortForecast": "Mostly Clear",
      "detailedForecast": ""
    },
    "401772948": {
      "temperatureF": 50,
      "windSpeedMph": 12.0,
      "shortForecast": "Mostly Clear",
      "detailedForecast": ""
    },
    "401762521": {
      "temperatureF": 33,
      "windSpeedMph": 13.0,
      "shortForecast": "Mostly Clear",
      "detailedForecast": ""
    },
    "401778303": {
      "temperatureF": 39,
      "windSpeedMph": 5.0,
      "shortForecast": "Mostly Clear",
      "detailedForecast": ""
    }
  }
}